{
    "module": "FinalProjectAlice",
    "icon": "time",
    "description": "Takes care of final project alice",
    "slotTypes": [],
    "intents": [
        {
            "name": "NextMeeting",
            "description": "User asks for the next meeting",
            "enabledByDefault": true,
            "utterances": [
                "what is the next meeting",
                "what meeting is up next",
                "who is in here for the next meeting",
                "what meeting is happening next",
                "meeting up next",
                "what meeting",
                "next meeting"
            ],
            "slots": []
        },
        {
            "name": "AttendeeThere",
            "description": "Check if attendee is there",
            "enabledByDefault": true,
            "utterances": [
                "{not at all:=>Answer}",
                "{sure:=>Answer}",
                "{nope:=>Answer}",
                "{no thank you:=>Answer}",
                "{no thanks:=>Answer}",
                "{yes please:=>Answer}",
                "{yeah:=>Answer}",
                "{yep:=>Answer}",
                "{no:=>Answer}",
                "{yes:=>Answer}"
			],
            "slots": [
                {
                    "name": "Answer",
                    "description": null,
                    "required": false,
                    "type": "AnswerYesNo",
                    "missingQuestion": ""
                }
            ]
        }
    ]
}